ole/__init__.py
ole/constants.py
ole/file.py
ole/storage.py
ole/stream.py
ole/structures.py
ole/utils.py
ole_py-1.1.2.dist-info/LICENSE
ole_py-1.1.2.dist-info/METADATA
ole_py-1.1.2.dist-info/WHEEL
ole_py-1.1.2.dist-info/top_level.txt
ole_py-1.1.2.dist-info/RECORD
