Metadata-Version: 2.1
Name: ole-py
Version: 1.1.2
Summary: Lightweight Microsoft OLE file parser in pure Python
Home-page: https://github.com/hallazzang/ole-py
Author: Hanjun Kim
Author-email: hallazzang@gmail.com
License: MIT
Platform: UNKNOWN
Classifier: Intended Audience :: Developers
Classifier: License :: OSI Approved :: MIT License
Classifier: Operating System :: OS Independent
Classifier: Programming Language :: Python
Classifier: Programming Language :: Python :: 3
Classifier: Programming Language :: Python :: 3.5
Classifier: Programming Language :: Python :: 3.6
Classifier: Programming Language :: Python :: 3.7
Classifier: Topic :: Software Development :: Libraries :: Python Modules
Requires-Python: >=3.5
